sfs2x/__init__.py
sfs2x/core/__init__.py
sfs2x/core/buffer.py
sfs2x/core/exceptions.py
sfs2x/core/field.py
sfs2x/core/registry.py
sfs2x/core/type_codes.py
sfs2x/core/utils.py
sfs2x/core/types/__init__.py
sfs2x/core/types/arrays.py
sfs2x/core/types/containers.py
sfs2x/core/types/containers.pyi
sfs2x/core/types/primitives.py
sfs2x/protocol/__init__.py
sfs2x/protocol/codec.py
sfs2x/protocol/constants.py
sfs2x/protocol/exceptions.py
sfs2x/protocol/message.py
sfs2x/protocol/security.py
sfs2x/transport/__init__.py
sfs2x/transport/base.py
sfs2x/transport/factory.py
sfs2x/transport/tcp.py
sfs2x-0.1.0.1.dist-info/licenses/LICENSE
sfs2x-0.1.0.1.dist-info/METADATA
sfs2x-0.1.0.1.dist-info/WHEEL
sfs2x-0.1.0.1.dist-info/top_level.txt
sfs2x-0.1.0.1.dist-info/RECORD
