Metadata-Version: 2.4
Name: sfs2x
Version: 0.1.0.1
Summary: Python-Based implementation of SmartFoxServer2X (SFS2X) Protocol.
Author-email: Zewsic <me@zewsic.pro>
License: MIT
License-File: LICENSE
Dynamic: license-file
